openpyxl_image_loader/__init__.py
openpyxl_image_loader/sheet_image_loader.py
openpyxl_image_loader-1.0.5.dist-info/LICENSE
openpyxl_image_loader-1.0.5.dist-info/METADATA
openpyxl_image_loader-1.0.5.dist-info/WHEEL
openpyxl_image_loader-1.0.5.dist-info/top_level.txt
openpyxl_image_loader-1.0.5.dist-info/RECORD
