Metadata-Version: 2.1
Name: openpyxl-image-loader
Version: 1.0.5
Summary: Openpyxl wrapper that gets images from cells
Home-page: https://github.com/mauricio-chavez/openpyxl-image-loader
Author: Mauricio Chávez Olea
Author-email: mauriciochavez@ciencias.unam.mx
License: MIT
Platform: UNKNOWN
Classifier: License :: OSI Approved :: MIT License
Classifier: Programming Language :: Python :: 3
Classifier: Programming Language :: Python :: 3.7
